taurex_ggchem/fort_ggchem.cpython-311-darwin.so
taurex_ggchem/__init__.py
taurex_ggchem/chemistry/ggchemistry_safe.py
taurex_ggchem/chemistry/__init__.py
taurex_ggchem/chemistry/ggchemistry.py
taurex_ggchem/.dylibs/libgfortran.5.dylib
taurex_ggchem/.dylibs/libquadmath.0.dylib
taurex_ggchem/.dylibs/libgcc_s.1.1.dylib
taurex_ggchem/data/abundances.pro
taurex_ggchem/data/EarthCrust.dat
taurex_ggchem/data/DustChem_GGchem.dat
taurex_ggchem/data/dispol_StockKitzmann.dat
taurex_ggchem/data/DustChem_Lee.dat
taurex_ggchem/data/dispol_StockKitzmann_withoutTsuji.dat
taurex_ggchem/data/dispol_GGchem.dat
taurex_ggchem/data/dispol_WoitkeRefit.dat
taurex_ggchem/data/dispol_fast.dat
taurex_ggchem/data/DustChem.dat
taurex_ggchem/data/DustChem_SH90.dat
taurex_ggchem/data/Abundances.dat
taurex_ggchem/data/DustChem_SUPCRTBL.dat
taurex_ggchem/data/Burcat_ref-elements.dat
taurex_ggchem/data/dispol_Tsuji.dat
taurex_ggchem/data/dispol_BarklemCollet.dat
taurex_ggchem/data/dispol_SharpHuebner.dat
taurex_ggchem/data/JANAF/K2SiO3_cr.txt
taurex_ggchem/data/JANAF/SiCl2.txt
taurex_ggchem/data/JANAF/FeCl2.txt
taurex_ggchem/data/JANAF/W2O6.txt
taurex_ggchem/data/JANAF/Mg2Cl4.txt
taurex_ggchem/data/JANAF/H2WO4.txt
taurex_ggchem/data/JANAF/FeS_cr.txt
taurex_ggchem/data/JANAF/FeS.txt
taurex_ggchem/data/JANAF/MgCl.txt
taurex_ggchem/data/JANAF/Caatom.txt
taurex_ggchem/data/JANAF/SiH.txt
taurex_ggchem/data/JANAF/S7.txt
taurex_ggchem/data/JANAF/AlCl3_cr.txt
taurex_ggchem/data/JANAF/He+.txt
taurex_ggchem/data/JANAF/KF.txt
taurex_ggchem/data/JANAF/H+.txt
taurex_ggchem/data/JANAF/Na2O2H2.txt
taurex_ggchem/data/JANAF/Na2SiO3_cr.txt
taurex_ggchem/data/JANAF/FeCl3.txt
taurex_ggchem/data/JANAF/SiCl3.txt
taurex_ggchem/data/JANAF/CaO_l.txt
taurex_ggchem/data/JANAF/LiO.txt
taurex_ggchem/data/JANAF/MgO_cr.txt
taurex_ggchem/data/JANAF/CaCl.txt
taurex_ggchem/data/JANAF/Zr_l.txt
taurex_ggchem/data/JANAF/Li2SiO3_l.txt
taurex_ggchem/data/JANAF/KCl_cr.txt
taurex_ggchem-1.1.1.dist-info/RECORD
taurex_ggchem-1.1.1.dist-info/WHEEL
taurex_ggchem-1.1.1.dist-info/entry_points.txt
taurex_ggchem-1.1.1.dist-info/METADATA
