Metadata-Version: 2.1
Name: taurex_ggchem
Version: 1.1.1
Summary: Taurex Python wrapper for the FORTRAN GGChem code.
Keywords: taurex,taurex3,exoplanet,exoplanets,transmission,spectroscopy,atmospheres,atmosphere,chemistry,equilibrium-chemistry,chemistry-solver,chemistry-equilibrium,chemistry-equilibrium-solver,fortran
Author-Email: "Ahmed F. Al-Refaie" <ahmed.al-refaie.12@ucl.ac.uk>
Maintainer-Email: "Ahmed F. Al-Refaie" <ahmed.al-refaie.12@ucl.ac.uk>
Classifier: Development Status :: 5 - Production/Stable
Classifier: Intended Audience :: Developers
Classifier: Intended Audience :: Education
Classifier: Intended Audience :: Science/Research
Classifier: License :: OSI Approved :: BSD License
Classifier: Operating System :: Unix
Classifier: Operating System :: MacOS
Classifier: Operating System :: POSIX :: Linux
Classifier: Operating System :: Microsoft :: Windows
Classifier: Programming Language :: Fortran
Classifier: Programming Language :: Python :: 3
Classifier: Programming Language :: Python :: 3.10
Classifier: Programming Language :: Python :: 3.11
Classifier: Programming Language :: Python :: 3.12
Classifier: Programming Language :: Python :: 3.13
Classifier: Topic :: Scientific/Engineering
Classifier: Topic :: Software Development :: Libraries
Classifier: Topic :: Software Development :: Libraries :: Python Modules
Project-URL: source, https://github.com/ucl-exoplanets/GGchem
Requires-Python: >=3.10
Requires-Dist: numpy>=2.0.2
Requires-Dist: taurex>=3.3.0
